ToShuangYue/FirstLetter.py
ToShuangYue/__init__.py
ToShuangYue-1.0.0.dist-info/METADATA
ToShuangYue-1.0.0.dist-info/WHEEL
ToShuangYue-1.0.0.dist-info/top_level.txt
ToShuangYue-1.0.0.dist-info/RECORD
