Metadata-Version: 2.1
Name: ToShuangYue
Version: 1.0.0
Summary: ToShuangYue contact way
Home-page: https://github.com
Author: DMY
Author-email: 2023020560@hrbmu.edu.cn
Requires-Python: >=3.6
